pydetour.py
pydetour-0.1.0.dist-info/METADATA
pydetour-0.1.0.dist-info/WHEEL
pydetour-0.1.0.dist-info/top_level.txt
pydetour-0.1.0.dist-info/RECORD
