Metadata-Version: 2.1
Name: pydetour
Version: 0.1.0
Summary: Redirect any callable objects in Python, by manipulating tp_vectorcall of a PyObject with ctypes
Home-page: https://github.com/atodekangae/pydetour
Author: atodekangae
Author-email: atodekangae@gmail.com
License: UNKNOWN
Project-URL: Source, https://github.com/atodekangae/pydetour
Keywords: ctypes,detour,hook
Platform: UNKNOWN
Classifier: Programming Language :: Python :: 3.8
Classifier: Programming Language :: Python :: 3.9
Classifier: Programming Language :: Python :: 3.10
Requires-Python: >=3.8
